doujindown/__init__.py
doujindown/app.py
doujindown/read_serialized.py
doujindown/requirements.txt
doujindown/text_cleaning.py
doujindown/conf/doujindown.txt
doujindown/conf/mirrors.json
doujindown/conf/settings.yml
doujindown/conf/working.csv
doujindown/scrapers/abstract_scraper.py
doujindown/scrapers/hitomi.py
doujindown/scrapers/manganelo.py
doujindown/scrapers/__pycache__/abstract_scraper.cpython-38.pyc
doujindown/scrapers/__pycache__/manganelo.cpython-38.pyc
doujindown-0.0.5.dist-info/METADATA
doujindown-0.0.5.dist-info/WHEEL
doujindown-0.0.5.dist-info/entry_points.txt
doujindown-0.0.5.dist-info/top_level.txt
doujindown-0.0.5.dist-info/RECORD
