Metadata-Version: 2.1
Name: doujindown
Version: 0.0.5
Summary: cli app to download doujins + manga from lots of websites *manganelo.com hitomi.la
Home-page: https://github.com/hashirkz/doujindown
Author: hashirkz
Author-email: hashirxkhan1@gmail.com
Classifier: Programming Language :: Python :: 3
Classifier: Operating System :: POSIX
Requires-Dist: numpy (==1.24.3)
Requires-Dist: pandas (==2.0.2)
Requires-Dist: requests (==2.28.1)
Requires-Dist: bs4 (==0.0.1)
Requires-Dist: tabulate (==0.9.0)
Requires-Dist: urllib3 (==1.26.12)
Requires-Dist: pillow (==10.0.0)
Requires-Dist: matplotlib (==3.7.2)
Requires-Dist: pyyaml (==6.0.1)
